pytoxo/__init__.py
pytoxo/calculations.py
pytoxo/errors.py
pytoxo/model.py
pytoxo/ptable.py
pytoxo/util.py
pytoxo-1.2.data/data/LICENSE
pytoxo-1.2.data/data/README.md
pytoxo-1.2.data/data/requirements_with_gui.txt
pytoxo_cli/__init__.py
pytoxo_cli/__main__.py
pytoxo_gui/__init__.py
pytoxo_gui/__main__.py
pytoxo-1.2.dist-info/LICENSE
pytoxo-1.2.dist-info/METADATA
pytoxo-1.2.dist-info/WHEEL
pytoxo-1.2.dist-info/entry_points.txt
pytoxo-1.2.dist-info/top_level.txt
pytoxo-1.2.dist-info/RECORD
