Metadata-Version: 2.1
Name: pytoxo
Version: 1.2
Summary: A Python tool to calculate penetrance tables for high-order epistasis models
Home-page: https://github.com/bglezseoane/pytoxo
Author: Borja González Seoane
Author-email: borja.gseoane@udc.es
License: LICENSE
Download-URL: https://github.com/bglezseoane/pytoxo/archive/1.2.tar.gz
Platform: UNKNOWN
Classifier: Intended Audience :: Science/Research
Classifier: Topic :: Scientific/Engineering
Classifier: Topic :: Scientific/Engineering :: Bio-Informatics
Classifier: Operating System :: OS Independent
Classifier: Development Status :: 2 - Pre-Alpha
Classifier: License :: OSI Approved :: GNU General Public License v3 (GPLv3)
Classifier: Programming Language :: Python
Classifier: Programming Language :: Python :: 3
Requires-Python: >=3.8
Requires-Dist: colorama (==0.4.4)
Requires-Dist: mpmath (==1.2.1)
Requires-Dist: numpy (==1.20.3)
Requires-Dist: Pillow (==9.0.1)
Requires-Dist: PySimpleGUI (==4.43.0)
Requires-Dist: sympy (==1.8)
Requires-Dist: termcolor (==1.1.0)
